dcd_lago-1.0.1.dist-info/licenses/LICENSE.txt
lago/__init__.py
lago/l_modularity_function.py
lago/lago.py
lago/leaf.py
lago/linkstream.py
lago/module.py
lago/plot.py
lago/tools.py
dcd_lago-1.0.1.dist-info/METADATA
dcd_lago-1.0.1.dist-info/WHEEL
dcd_lago-1.0.1.dist-info/top_level.txt
dcd_lago-1.0.1.dist-info/RECORD
