Metadata-Version: 2.4
Name: dcd-lago
Version: 1.0.1
Summary: Python implementation of the LAGO method for dynamic community detection in temporal networks. Derived functions such as the Longitudinal Modularity are also provided.
Author-email: Victor Brabant <victorbrabant@gmail.com>
License: MIT
Project-URL: Homepage, https://github.com/fondationsahar/dynamic_community_detection
Project-URL: Issues, https://github.com/fondationsahar/dynamic_community_detection/issues
Keywords: lago,networks,temporal networks,modularity,longitudinal modularity,community detection,dynamic community detection
Requires-Python: >=3.11
License-File: LICENSE.txt
Dynamic: license-file
